<completion-snapshots>
    <completion-snapshot name="s">
        <script>
            <input>
                s
            </input>
        </script>
        <cursor>
            <search text="s" index="1" />
        </cursor>
        <completions limit="3" />
    </completion-snapshot>
    <completion-snapshot name="se">
        <script>
            <input>
                se
            </input>
        </script>
        <cursor>
            <search text="se" index="2" />
        </cursor>
        <completions limit="3" />
    </completion-snapshot>
    <completion-snapshot name="sel">
        <script>
            <input>
                sel
            </input>
        </script>
        <cursor>
            <search text="sel" index="3" />
        </cursor>
        <completions limit="3" />
    </completion-snapshot>
    <completion-snapshot name="select_star">
        <script>
            <input>
                select *
            </input>
        </script>
        <cursor>
            <search text="*" index="1" />
        </cursor>
        <completions limit="3" />
    </completion-snapshot>
    <completion-snapshot name="select_f">
        <script>
            <input>
                select * f
            </input>
        </script>
        <cursor>
            <search text="f" index="1" />
        </cursor>
        <completions limit="3" />
    </completion-snapshot>
    <completion-snapshot name="select_fr">
        <script>
            <input>
                select * fr
            </input>
        </script>
        <cursor>
            <search text="fr" index="2" />
        </cursor>
        <completions limit="3" />
    </completion-snapshot>
    <completion-snapshot name="select_from">
        <script>
            <input>
                select * from
            </input>
        </script>
        <cursor>
            <search text="fr" index="4" />
        </cursor>
        <completions limit="3" />
    </completion-snapshot>
    <completion-snapshot name="select_from_eof">
        <script>
            <input>
                select * from a xx
            </input>
        </script>
        <cursor>
            <search text="xx" index="0" />
        </cursor>
        <completions limit="3" />
    </completion-snapshot>
    <completion-snapshot name="select_from_w">
        <script>
            <input>
                select * from a w
            </input>
        </script>
        <cursor>
            <search text="w" index="1" />
        </cursor>
        <completions limit="3" />
    </completion-snapshot>
    <completion-snapshot name="select_from_wh">
        <script>
            <input>
                select * from a wh
            </input>
        </script>
        <cursor>
            <search text="wh" index="2" />
        </cursor>
        <completions limit="3" />
    </completion-snapshot>
    <completion-snapshot name="selec">
        <script>
            <input>
                selec
            </input>
        </script>
        <cursor>
            <search text="selec" index="5" />
        </cursor>
        <completions limit="3" />
    </completion-snapshot>
    <completion-snapshot name="gr">
        <script>
            <input>
                select * from foo gr
            </input>
        </script>
        <cursor>
            <search text="gr" index="1" />
        </cursor>
        <completions limit="3" />
    </completion-snapshot>
    <completion-snapshot name="group">
        <script>
            <input>
                select * from foo group
            </input>
        </script>
        <cursor>
            <search text="group" index="4" />
        </cursor>
        <completions limit="3" />
    </completion-snapshot>
    <completion-snapshot name="group_b">
        <script>
            <input>
                select * from foo group b
            </input>
        </script>
        <cursor>
            <search text="b" index="1" />
        </cursor>
        <completions limit="3" />
    </completion-snapshot>
    <completion-snapshot name="group_eof">
        <script>
            <input>
                select * from foo group xx
            </input>
        </script>
        <cursor>
            <search text="xx" index="0" />
        </cursor>
        <completions limit="3" />
    </completion-snapshot>
    <completion-snapshot name="from_o">
        <script>
            <input>
                select * from foo o
            </input>
        </script>
        <cursor>
            <search text="foo o" index="5" />
        </cursor>
        <completions limit="3" />
    </completion-snapshot>
    <completion-snapshot name="from_or">
        <script>
            <input>
                select * from foo or
            </input>
        </script>
        <cursor>
            <search text="or" index="1" />
        </cursor>
        <completions limit="3" />
    </completion-snapshot>
    <completion-snapshot name="from_order">
        <script>
            <input>
                select * from foo order
            </input>
        </script>
        <cursor>
            <search text="order" index="5" />
        </cursor>
        <completions limit="3" />
    </completion-snapshot>
</completion-snapshots>
